abstract_related_model
